sskie/__init__.py
sskie/spatial_analysis.py
sskie/spatial_operators.py
sskie/data/__init__.py
sskie/data/building_seoul_5179.geojson
sskie/data/mapo-gu.geojson
sskie/data/subway_5179.geojson
sskie/data/마포구_all_store.txt
sskie/data/마포구_음식업_store.txt
sskie/data/상위100_지하철역 출입구.csv
sskie/data/실거래가_서울.txt
sskie/data/전체_지하철역 출입구.csv
sskie/data/지하철역 출입구_5179.geojson
sskie/data/직방_서울_5179.geojson
sskie-0.4.2.dist-info/METADATA
sskie-0.4.2.dist-info/WHEEL
sskie-0.4.2.dist-info/top_level.txt
sskie-0.4.2.dist-info/RECORD
