Metadata-Version: 2.1
Name: sskie
Version: 0.4.2
Summary: prototype-used-in-sskie
Home-page: 
Author: knut_urban
Author-email: tnekf0314@ut.ac.kr
Requires-Python: >=3.8.6
Requires-Dist: pandas
Requires-Dist: numpy
Requires-Dist: scipy
Requires-Dist: geopandas
Requires-Dist: pydeck
Requires-Dist: simplejson
